hawhodid/__init__.py
hawhodid-0.0.1.dist-info/licenses/LICENSE
hawhodid-0.0.1.dist-info/METADATA
hawhodid-0.0.1.dist-info/WHEEL
hawhodid-0.0.1.dist-info/top_level.txt
hawhodid-0.0.1.dist-info/RECORD
